trackers/__init__.py
trackers/export.py
trackers/performance.py
PerforMate-0.1.5.dist-info/LICENSE
PerforMate-0.1.5.dist-info/METADATA
PerforMate-0.1.5.dist-info/WHEEL
PerforMate-0.1.5.dist-info/top_level.txt
PerforMate-0.1.5.dist-info/RECORD
