Metadata-Version: 2.1
Name: PerforMate
Version: 0.1.5
Summary: A lightweight performance tracker for python projects.
Home-page: https://github.com/kreateyou/PerforMate
Author: Elijah M
Author-email: elijah@kreateyou.com
Classifier: Programming Language :: Python :: 3
Classifier: License :: OSI Approved :: MIT License
Classifier: Operating System :: OS Independent
Requires-Python: >=3.6
License-File: LICENSE
Requires-Dist: tinydb
Requires-Dist: pandas
Requires-Dist: matplotlib
Requires-Dist: numpy
